my_weekly_schedule/__init__.py
my_weekly_schedule/main.py
my_weekly_schedule/models.py
my_weekly_schedule/parse_txt.py
my_weekly_schedule/plot_schedule.py
my_weekly_schedule-0.1.4.dist-info/LICENSE
my_weekly_schedule-0.1.4.dist-info/METADATA
my_weekly_schedule-0.1.4.dist-info/WHEEL
my_weekly_schedule-0.1.4.dist-info/entry_points.txt
my_weekly_schedule-0.1.4.dist-info/RECORD
