Metadata-Version: 2.1
Name: my-weekly-schedule
Version: 0.1.4
Summary: A tool for plotting your weekly schedule.
Home-page: https://github.com/ftorres16/my_weekly_schedule
License: GPL-3.0-or-later
Author: Fabian Torres
Requires-Python: >=3.9,<4.0
Classifier: License :: OSI Approved :: GNU General Public License v3 or later (GPLv3+)
Classifier: Programming Language :: Python :: 3
Classifier: Programming Language :: Python :: 3.9
Classifier: Programming Language :: Python :: 3.10
Classifier: Programming Language :: Python :: 3.11
Requires-Dist: matplotlib (>=3.5.1,<4.0.0)
Requires-Dist: pydantic (>=1.9.0,<2.0.0)
Requires-Dist: typer (>=0.4.0,<0.5.0)
Project-URL: Repository, https://github.com/ftorres16/my_weekly_schedule
